observational_learn/__init__.py
observational_learn/matching/__init__.py
observational_learn/matching/_pairmatching.py
observational_learn-0.0.7.dist-info/METADATA
observational_learn-0.0.7.dist-info/WHEEL
observational_learn-0.0.7.dist-info/licenses/LICENSE
observational_learn-0.0.7.dist-info/RECORD
