Metadata-Version: 2.4
Name: observational_learn
Version: 0.0.7
Summary: A Python package for causal methods in observational studies
Project-URL: Homepage, https://github.com/pypa/sampleproject
Project-URL: Issues, https://github.com/pypa/sampleproject/issues
Author-email: jorgelh <author@example.com>
License-Expression: MIT
License-File: LICENSE
Classifier: Operating System :: OS Independent
Classifier: Programming Language :: Python :: 3
Requires-Python: >=3.9
Requires-Dist: pandas>=2.0
Requires-Dist: scipy>=1.8
